[
  {
    "hour": 0,
    "validSamples": 3600,
    "averageHz": 49.99178666666667,
    "minimumHz": 49.892,
    "maximumHz": 50.044,
    "standardDeviationHz": 0.03437551680419608,
    "meanAbsoluteDeviationFrom50Mhz": 24.953888888889214
  },
  {
    "hour": 1,
    "validSamples": 3600,
    "averageHz": 50.004245000000004,
    "minimumHz": 49.945,
    "maximumHz": 50.06,
    "standardDeviationHz": 0.021002340544171307,
    "meanAbsoluteDeviationFrom50Mhz": 17.507222222222563
  },
  {
    "hour": 2,
    "validSamples": 3600,
    "averageHz": 50.01020444444445,
    "minimumHz": 49.948,
    "maximumHz": 50.057,
    "standardDeviationHz": 0.018680363493436623,
    "meanAbsoluteDeviationFrom50Mhz": 18.176666666666957
  },
  {
    "hour": 3,
    "validSamples": 3600,
    "averageHz": 50.0035325,
    "minimumHz": 49.95,
    "maximumHz": 50.047,
    "standardDeviationHz": 0.015028511768376438,
    "meanAbsoluteDeviationFrom50Mhz": 12.56694444444476
  },
  {
    "hour": 4,
    "validSamples": 3600,
    "averageHz": 49.995670833333335,
    "minimumHz": 49.954,
    "maximumHz": 50.06,
    "standardDeviationHz": 0.01704291101813984,
    "meanAbsoluteDeviationFrom50Mhz": 14.69305555555593
  },
  {
    "hour": 5,
    "validSamples": 3600,
    "averageHz": 49.98752888888889,
    "minimumHz": 49.936,
    "maximumHz": 50.085,
    "standardDeviationHz": 0.021020393507493615,
    "meanAbsoluteDeviationFrom50Mhz": 20.800555555555786
  },
  {
    "hour": 6,
    "validSamples": 3600,
    "averageHz": 49.98372555555556,
    "minimumHz": 49.892,
    "maximumHz": 50.143,
    "standardDeviationHz": 0.04765562473765089,
    "meanAbsoluteDeviationFrom50Mhz": 40.483888888888906
  },
  {
    "hour": 7,
    "validSamples": 3600,
    "averageHz": 49.984813055555556,
    "minimumHz": 49.925,
    "maximumHz": 50.067,
    "standardDeviationHz": 0.029178051046733697,
    "meanAbsoluteDeviationFrom50Mhz": 27.949722222222228
  },
  {
    "hour": 8,
    "validSamples": 3600,
    "averageHz": 49.99425333333333,
    "minimumHz": 49.95,
    "maximumHz": 50.031,
    "standardDeviationHz": 0.011199540665184384,
    "meanAbsoluteDeviationFrom50Mhz": 10.150555555555847
  },
  {
    "hour": 9,
    "validSamples": 3600,
    "averageHz": 50.005314999999996,
    "minimumHz": 49.956,
    "maximumHz": 50.045,
    "standardDeviationHz": 0.017708086586516406,
    "meanAbsoluteDeviationFrom50Mhz": 15.435555555555796
  },
  {
    "hour": 10,
    "validSamples": 3600,
    "averageHz": 49.99968222222222,
    "minimumHz": 49.897,
    "maximumHz": 50.043,
    "standardDeviationHz": 0.025986516066682817,
    "meanAbsoluteDeviationFrom50Mhz": 19.462777777778115
  },
  {
    "hour": 11,
    "validSamples": 3600,
    "averageHz": 49.98929944444445,
    "minimumHz": 49.923,
    "maximumHz": 50.038,
    "standardDeviationHz": 0.019019852193672235,
    "meanAbsoluteDeviationFrom50Mhz": 16.47722222222247
  },
  {
    "hour": 12,
    "validSamples": 3600,
    "averageHz": 49.99878194444444,
    "minimumHz": 49.936,
    "maximumHz": 50.039,
    "standardDeviationHz": 0.018839850099581494,
    "meanAbsoluteDeviationFrom50Mhz": 15.21750000000036
  },
  {
    "hour": 13,
    "validSamples": 3600,
    "averageHz": 49.999048055555555,
    "minimumHz": 49.956,
    "maximumHz": 50.056,
    "standardDeviationHz": 0.02233915773795774,
    "meanAbsoluteDeviationFrom50Mhz": 18.238611111111283
  },
  {
    "hour": 14,
    "validSamples": 3600,
    "averageHz": 50.00251416666667,
    "minimumHz": 49.967,
    "maximumHz": 50.039,
    "standardDeviationHz": 0.013211077816868182,
    "meanAbsoluteDeviationFrom50Mhz": 11.33583333333372
  },
  {
    "hour": 15,
    "validSamples": 3600,
    "averageHz": 49.999525000000006,
    "minimumHz": 49.96,
    "maximumHz": 50.043,
    "standardDeviationHz": 0.014253379228956803,
    "meanAbsoluteDeviationFrom50Mhz": 11.654444444444826
  },
  {
    "hour": 16,
    "validSamples": 3600,
    "averageHz": 49.99351083333333,
    "minimumHz": 49.936,
    "maximumHz": 50.048,
    "standardDeviationHz": 0.01946931758134684,
    "meanAbsoluteDeviationFrom50Mhz": 17.106944444444725
  },
  {
    "hour": 17,
    "validSamples": 3600,
    "averageHz": 49.99746944444444,
    "minimumHz": 49.949,
    "maximumHz": 50.074,
    "standardDeviationHz": 0.02120434074330143,
    "meanAbsoluteDeviationFrom50Mhz": 16.568888888889237
  },
  {
    "hour": 18,
    "validSamples": 3600,
    "averageHz": 49.997037222222225,
    "minimumHz": 49.96,
    "maximumHz": 50.051,
    "standardDeviationHz": 0.014770682413166663,
    "meanAbsoluteDeviationFrom50Mhz": 12.718888888889273
  },
  {
    "hour": 19,
    "validSamples": 3600,
    "averageHz": 50.00153472222222,
    "minimumHz": 49.951,
    "maximumHz": 50.042,
    "standardDeviationHz": 0.018617193813204102,
    "meanAbsoluteDeviationFrom50Mhz": 15.664166666667072
  },
  {
    "hour": 20,
    "validSamples": 3600,
    "averageHz": 50.00573333333334,
    "minimumHz": 49.938,
    "maximumHz": 50.052,
    "standardDeviationHz": 0.024586999726594387,
    "meanAbsoluteDeviationFrom50Mhz": 21.460555555555704
  },
  {
    "hour": 21,
    "validSamples": 3600,
    "averageHz": 50.01038472222223,
    "minimumHz": 49.92,
    "maximumHz": 50.061,
    "standardDeviationHz": 0.029712988927974658,
    "meanAbsoluteDeviationFrom50Mhz": 27.101388888888966
  },
  {
    "hour": 22,
    "validSamples": 3600,
    "averageHz": 49.98626222222222,
    "minimumHz": 49.914,
    "maximumHz": 50.038,
    "standardDeviationHz": 0.02418411130279917,
    "meanAbsoluteDeviationFrom50Mhz": 21.392222222222397
  },
  {
    "hour": 23,
    "validSamples": 3600,
    "averageHz": 49.996428888888886,
    "minimumHz": 49.919,
    "maximumHz": 50.087,
    "standardDeviationHz": 0.030252032969131884,
    "meanAbsoluteDeviationFrom50Mhz": 23.860000000000266
  }
]
