[
  {
    "hour": 0,
    "validSamples": 3600,
    "averageHz": 50.00581388888889,
    "minimumHz": 49.949,
    "maximumHz": 50.055,
    "standardDeviationHz": 0.01901973613524456,
    "meanAbsoluteDeviationFrom50Mhz": 16.540555555555855
  },
  {
    "hour": 1,
    "validSamples": 3600,
    "averageHz": 50.01044333333333,
    "minimumHz": 49.962,
    "maximumHz": 50.054,
    "standardDeviationHz": 0.017669185669470695,
    "meanAbsoluteDeviationFrom50Mhz": 17.444444444444773
  },
  {
    "hour": 2,
    "validSamples": 3600,
    "averageHz": 49.999536111111105,
    "minimumHz": 49.95,
    "maximumHz": 50.039,
    "standardDeviationHz": 0.016473440792476323,
    "meanAbsoluteDeviationFrom50Mhz": 13.139444444444798
  },
  {
    "hour": 3,
    "validSamples": 3600,
    "averageHz": 49.997997222222224,
    "minimumHz": 49.947,
    "maximumHz": 50.042,
    "standardDeviationHz": 0.016507927154873994,
    "meanAbsoluteDeviationFrom50Mhz": 13.535000000000348
  },
  {
    "hour": 4,
    "validSamples": 3600,
    "averageHz": 50.00111944444444,
    "minimumHz": 49.954,
    "maximumHz": 50.039,
    "standardDeviationHz": 0.014390299962985626,
    "meanAbsoluteDeviationFrom50Mhz": 11.757222222222614
  },
  {
    "hour": 5,
    "validSamples": 3600,
    "averageHz": 49.99869833333334,
    "minimumHz": 49.966,
    "maximumHz": 50.034,
    "standardDeviationHz": 0.012035345976655051,
    "meanAbsoluteDeviationFrom50Mhz": 9.85388888888924
  },
  {
    "hour": 6,
    "validSamples": 3600,
    "averageHz": 50.00185444444445,
    "minimumHz": 49.966,
    "maximumHz": 50.045,
    "standardDeviationHz": 0.013497116244353652,
    "meanAbsoluteDeviationFrom50Mhz": 11.083333333333837
  },
  {
    "hour": 7,
    "validSamples": 3600,
    "averageHz": 49.99995944444444,
    "minimumHz": 49.957,
    "maximumHz": 50.063,
    "standardDeviationHz": 0.01701349202258248,
    "meanAbsoluteDeviationFrom50Mhz": 13.541666666666936
  },
  {
    "hour": 8,
    "validSamples": 3600,
    "averageHz": 50.00334388888889,
    "minimumHz": 49.949,
    "maximumHz": 50.052,
    "standardDeviationHz": 0.018781286974861616,
    "meanAbsoluteDeviationFrom50Mhz": 15.656111111111377
  },
  {
    "hour": 9,
    "validSamples": 3600,
    "averageHz": 50.00647722222222,
    "minimumHz": 49.948,
    "maximumHz": 50.053,
    "standardDeviationHz": 0.020533401868271975,
    "meanAbsoluteDeviationFrom50Mhz": 17.782777777778023
  },
  {
    "hour": 10,
    "validSamples": 3600,
    "averageHz": 49.997258888888894,
    "minimumHz": 49.936,
    "maximumHz": 50.062,
    "standardDeviationHz": 0.02567845354656724,
    "meanAbsoluteDeviationFrom50Mhz": 22.230000000000263
  },
  {
    "hour": 11,
    "validSamples": 3600,
    "averageHz": 49.997991666666664,
    "minimumHz": 49.852,
    "maximumHz": 50.071,
    "standardDeviationHz": 0.032374483050355916,
    "meanAbsoluteDeviationFrom50Mhz": 22.35444444444464
  },
  {
    "hour": 12,
    "validSamples": 3600,
    "averageHz": 49.99391444444444,
    "minimumHz": 49.939,
    "maximumHz": 50.04,
    "standardDeviationHz": 0.01715110661224803,
    "meanAbsoluteDeviationFrom50Mhz": 14.463333333333608
  },
  {
    "hour": 13,
    "validSamples": 3600,
    "averageHz": 50.00170555555556,
    "minimumHz": 49.944,
    "maximumHz": 50.038,
    "standardDeviationHz": 0.015936365549070092,
    "meanAbsoluteDeviationFrom50Mhz": 12.865555555555872
  },
  {
    "hour": 14,
    "validSamples": 3600,
    "averageHz": 50.01411,
    "minimumHz": 49.941,
    "maximumHz": 50.06,
    "standardDeviationHz": 0.02127387834881067,
    "meanAbsoluteDeviationFrom50Mhz": 21.45666666666673
  },
  {
    "hour": 15,
    "validSamples": 3600,
    "averageHz": 49.99965888888889,
    "minimumHz": 49.956,
    "maximumHz": 50.044,
    "standardDeviationHz": 0.01531797342589915,
    "meanAbsoluteDeviationFrom50Mhz": 12.607777777778162
  },
  {
    "hour": 16,
    "validSamples": 3600,
    "averageHz": 49.99760111111111,
    "minimumHz": 49.953,
    "maximumHz": 50.06,
    "standardDeviationHz": 0.019766998279649294,
    "meanAbsoluteDeviationFrom50Mhz": 16.601111111111333
  },
  {
    "hour": 17,
    "validSamples": 3600,
    "averageHz": 49.996409444444446,
    "minimumHz": 49.929,
    "maximumHz": 50.085,
    "standardDeviationHz": 0.03574308977072382,
    "meanAbsoluteDeviationFrom50Mhz": 30.46166666666681
  },
  {
    "hour": 18,
    "validSamples": 3600,
    "averageHz": 50.00196444444445,
    "minimumHz": 49.917,
    "maximumHz": 50.109,
    "standardDeviationHz": 0.037937007177428414,
    "meanAbsoluteDeviationFrom50Mhz": 29.743333333333553
  },
  {
    "hour": 19,
    "validSamples": 3600,
    "averageHz": 50.009034444444445,
    "minimumHz": 49.925,
    "maximumHz": 50.094,
    "standardDeviationHz": 0.035121581402990903,
    "meanAbsoluteDeviationFrom50Mhz": 29.69777777777791
  },
  {
    "hour": 20,
    "validSamples": 3600,
    "averageHz": 49.99073166666666,
    "minimumHz": 49.931,
    "maximumHz": 50.074,
    "standardDeviationHz": 0.02599999353632391,
    "meanAbsoluteDeviationFrom50Mhz": 22.25500000000013
  },
  {
    "hour": 21,
    "validSamples": 3600,
    "averageHz": 49.99722333333333,
    "minimumHz": 49.942,
    "maximumHz": 50.038,
    "standardDeviationHz": 0.018197881744862678,
    "meanAbsoluteDeviationFrom50Mhz": 14.76111111111139
  },
  {
    "hour": 22,
    "validSamples": 3600,
    "averageHz": 50.00636444444445,
    "minimumHz": 49.911,
    "maximumHz": 50.077,
    "standardDeviationHz": 0.027221610333259278,
    "meanAbsoluteDeviationFrom50Mhz": 20.90888888888909
  },
  {
    "hour": 23,
    "validSamples": 3600,
    "averageHz": 50.01068888888889,
    "minimumHz": 49.963,
    "maximumHz": 50.058,
    "standardDeviationHz": 0.015481418571554132,
    "meanAbsoluteDeviationFrom50Mhz": 15.480000000000317
  }
]
