[
  {
    "hour": 0,
    "validSamples": 3600,
    "averageHz": 49.99907416666667,
    "minimumHz": 49.908,
    "maximumHz": 50.052,
    "standardDeviationHz": 0.02886867389817021,
    "meanAbsoluteDeviationFrom50Mhz": 23.618611111111324
  },
  {
    "hour": 1,
    "validSamples": 3600,
    "averageHz": 50.00187611111111,
    "minimumHz": 49.927,
    "maximumHz": 50.045,
    "standardDeviationHz": 0.018784130015311,
    "meanAbsoluteDeviationFrom50Mhz": 14.867222222222503
  },
  {
    "hour": 2,
    "validSamples": 3600,
    "averageHz": 50.00096111111111,
    "minimumHz": 49.956,
    "maximumHz": 50.054,
    "standardDeviationHz": 0.014304142325016657,
    "meanAbsoluteDeviationFrom50Mhz": 11.55555555555593
  },
  {
    "hour": 3,
    "validSamples": 3600,
    "averageHz": 49.99648555555555,
    "minimumHz": 49.938,
    "maximumHz": 50.037,
    "standardDeviationHz": 0.01682053349075429,
    "meanAbsoluteDeviationFrom50Mhz": 12.905555555555843
  },
  {
    "hour": 4,
    "validSamples": 3600,
    "averageHz": 49.997209444444444,
    "minimumHz": 49.961,
    "maximumHz": 50.031,
    "standardDeviationHz": 0.012062661385091183,
    "meanAbsoluteDeviationFrom50Mhz": 10.091666666667063
  },
  {
    "hour": 5,
    "validSamples": 3600,
    "averageHz": 49.99111194444444,
    "minimumHz": 49.945,
    "maximumHz": 50.047,
    "standardDeviationHz": 0.017124737519390892,
    "meanAbsoluteDeviationFrom50Mhz": 16.38305555555598
  },
  {
    "hour": 6,
    "validSamples": 3600,
    "averageHz": 49.99660444444445,
    "minimumHz": 49.954,
    "maximumHz": 50.058,
    "standardDeviationHz": 0.016383687084082988,
    "meanAbsoluteDeviationFrom50Mhz": 13.608888888889304
  },
  {
    "hour": 7,
    "validSamples": 3600,
    "averageHz": 50.01437555555556,
    "minimumHz": 49.965,
    "maximumHz": 50.07,
    "standardDeviationHz": 0.0172429393673089,
    "meanAbsoluteDeviationFrom50Mhz": 18.811666666666866
  },
  {
    "hour": 8,
    "validSamples": 3600,
    "averageHz": 50.00986444444444,
    "minimumHz": 49.929,
    "maximumHz": 50.066,
    "standardDeviationHz": 0.025877606411340383,
    "meanAbsoluteDeviationFrom50Mhz": 23.0200000000002
  },
  {
    "hour": 9,
    "validSamples": 3600,
    "averageHz": 50.01419277777778,
    "minimumHz": 49.944,
    "maximumHz": 50.085,
    "standardDeviationHz": 0.030009906754187923,
    "meanAbsoluteDeviationFrom50Mhz": 27.956666666666752
  },
  {
    "hour": 10,
    "validSamples": 3600,
    "averageHz": 49.99615111111111,
    "minimumHz": 49.916,
    "maximumHz": 50.055,
    "standardDeviationHz": 0.024160825705373565,
    "meanAbsoluteDeviationFrom50Mhz": 19.910000000000263
  },
  {
    "hour": 11,
    "validSamples": 3600,
    "averageHz": 50.00879805555556,
    "minimumHz": 49.935,
    "maximumHz": 50.062,
    "standardDeviationHz": 0.024569505638702735,
    "meanAbsoluteDeviationFrom50Mhz": 22.13583333333354
  },
  {
    "hour": 12,
    "validSamples": 3600,
    "averageHz": 50.00761416666666,
    "minimumHz": 49.938,
    "maximumHz": 50.059,
    "standardDeviationHz": 0.019376181523114162,
    "meanAbsoluteDeviationFrom50Mhz": 17.181944444444785
  },
  {
    "hour": 13,
    "validSamples": 3600,
    "averageHz": 50.00776,
    "minimumHz": 49.963,
    "maximumHz": 50.055,
    "standardDeviationHz": 0.014890364520573778,
    "meanAbsoluteDeviationFrom50Mhz": 13.711111111111393
  },
  {
    "hour": 14,
    "validSamples": 3600,
    "averageHz": 49.994102222222224,
    "minimumHz": 49.944,
    "maximumHz": 50.046,
    "standardDeviationHz": 0.017086823889105134,
    "meanAbsoluteDeviationFrom50Mhz": 15.02444444444486
  },
  {
    "hour": 15,
    "validSamples": 3600,
    "averageHz": 49.998605833333336,
    "minimumHz": 49.929,
    "maximumHz": 50.084,
    "standardDeviationHz": 0.026514742636566,
    "meanAbsoluteDeviationFrom50Mhz": 20.874722222222342
  },
  {
    "hour": 16,
    "validSamples": 3600,
    "averageHz": 49.9928675,
    "minimumHz": 49.914,
    "maximumHz": 50.066,
    "standardDeviationHz": 0.02600341749708632,
    "meanAbsoluteDeviationFrom50Mhz": 22.059722222222348
  },
  {
    "hour": 17,
    "validSamples": 3600,
    "averageHz": 50.01542055555556,
    "minimumHz": 49.953,
    "maximumHz": 50.108,
    "standardDeviationHz": 0.03401639832855504,
    "meanAbsoluteDeviationFrom50Mhz": 28.773888888889104
  },
  {
    "hour": 18,
    "validSamples": 3600,
    "averageHz": 49.98949222222222,
    "minimumHz": 49.942,
    "maximumHz": 50.091,
    "standardDeviationHz": 0.030358907635807782,
    "meanAbsoluteDeviationFrom50Mhz": 27.436666666666827
  },
  {
    "hour": 19,
    "validSamples": 3600,
    "averageHz": 49.998022777777784,
    "minimumHz": 49.954,
    "maximumHz": 50.078,
    "standardDeviationHz": 0.023012171490939436,
    "meanAbsoluteDeviationFrom50Mhz": 18.428333333333736
  },
  {
    "hour": 20,
    "validSamples": 3600,
    "averageHz": 50.01277666666667,
    "minimumHz": 49.972,
    "maximumHz": 50.064,
    "standardDeviationHz": 0.015472434628504197,
    "meanAbsoluteDeviationFrom50Mhz": 16.41166666666695
  },
  {
    "hour": 21,
    "validSamples": 3600,
    "averageHz": 50.00522083333334,
    "minimumHz": 49.922,
    "maximumHz": 50.051,
    "standardDeviationHz": 0.023223751237209374,
    "meanAbsoluteDeviationFrom50Mhz": 19.352500000000283
  },
  {
    "hour": 22,
    "validSamples": 3600,
    "averageHz": 49.996920555555555,
    "minimumHz": 49.9,
    "maximumHz": 50.037,
    "standardDeviationHz": 0.02213368021119335,
    "meanAbsoluteDeviationFrom50Mhz": 16.19500000000034
  },
  {
    "hour": 23,
    "validSamples": 3600,
    "averageHz": 50.00215194444444,
    "minimumHz": 49.933,
    "maximumHz": 50.048,
    "standardDeviationHz": 0.019631181874118084,
    "meanAbsoluteDeviationFrom50Mhz": 16.20083333333371
  }
]
