[
  {
    "hour": 0,
    "validSamples": 3600,
    "averageHz": 49.99841277777777,
    "minimumHz": 49.936,
    "maximumHz": 50.04,
    "standardDeviationHz": 0.019973889986000262,
    "meanAbsoluteDeviationFrom50Mhz": 15.412777777777952
  },
  {
    "hour": 1,
    "validSamples": 3600,
    "averageHz": 49.99153638888889,
    "minimumHz": 49.921,
    "maximumHz": 50.038,
    "standardDeviationHz": 0.01950873901796304,
    "meanAbsoluteDeviationFrom50Mhz": 15.16861111111139
  },
  {
    "hour": 2,
    "validSamples": 3600,
    "averageHz": 49.98314499999999,
    "minimumHz": 49.907,
    "maximumHz": 50.033,
    "standardDeviationHz": 0.02816837425790389,
    "meanAbsoluteDeviationFrom50Mhz": 24.372777777778044
  },
  {
    "hour": 3,
    "validSamples": 3600,
    "averageHz": 49.987115555555555,
    "minimumHz": 49.945,
    "maximumHz": 50.039,
    "standardDeviationHz": 0.014315977174791064,
    "meanAbsoluteDeviationFrom50Mhz": 15.87000000000033
  },
  {
    "hour": 4,
    "validSamples": 3600,
    "averageHz": 49.99488,
    "minimumHz": 49.963,
    "maximumHz": 50.052,
    "standardDeviationHz": 0.012387943959978453,
    "meanAbsoluteDeviationFrom50Mhz": 11.018888888889231
  },
  {
    "hour": 5,
    "validSamples": 3600,
    "averageHz": 49.99718111111112,
    "minimumHz": 49.956,
    "maximumHz": 50.057,
    "standardDeviationHz": 0.017432360676782863,
    "meanAbsoluteDeviationFrom50Mhz": 14.650000000000437
  },
  {
    "hour": 6,
    "validSamples": 3600,
    "averageHz": 49.99171305555555,
    "minimumHz": 49.932,
    "maximumHz": 50.083,
    "standardDeviationHz": 0.0294468380984601,
    "meanAbsoluteDeviationFrom50Mhz": 25.412500000000357
  },
  {
    "hour": 7,
    "validSamples": 3600,
    "averageHz": 49.99843,
    "minimumHz": 49.955,
    "maximumHz": 50.059,
    "standardDeviationHz": 0.018463314677730547,
    "meanAbsoluteDeviationFrom50Mhz": 15.438888888889297
  },
  {
    "hour": 8,
    "validSamples": 3600,
    "averageHz": 49.99885472222223,
    "minimumHz": 49.891,
    "maximumHz": 50.078,
    "standardDeviationHz": 0.036529717809698034,
    "meanAbsoluteDeviationFrom50Mhz": 28.37194444444457
  },
  {
    "hour": 9,
    "validSamples": 3600,
    "averageHz": 50.00290111111111,
    "minimumHz": 49.876,
    "maximumHz": 50.104,
    "standardDeviationHz": 0.04422885180624478,
    "meanAbsoluteDeviationFrom50Mhz": 36.39611111111113
  },
  {
    "hour": 10,
    "validSamples": 3600,
    "averageHz": 50.00271027777778,
    "minimumHz": 49.887,
    "maximumHz": 50.092,
    "standardDeviationHz": 0.03369838777763309,
    "meanAbsoluteDeviationFrom50Mhz": 25.64194444444473
  },
  {
    "hour": 11,
    "validSamples": 3600,
    "averageHz": 50.00251333333333,
    "minimumHz": 49.903,
    "maximumHz": 50.062,
    "standardDeviationHz": 0.032595063361735684,
    "meanAbsoluteDeviationFrom50Mhz": 26.21444444444463
  },
  {
    "hour": 12,
    "validSamples": 3600,
    "averageHz": 50.03135416666667,
    "minimumHz": 49.968,
    "maximumHz": 50.079,
    "standardDeviationHz": 0.020788935608876007,
    "meanAbsoluteDeviationFrom50Mhz": 32.9597222222222
  },
  {
    "hour": 13,
    "validSamples": 3600,
    "averageHz": 50.008454722222226,
    "minimumHz": 49.935,
    "maximumHz": 50.055,
    "standardDeviationHz": 0.01985650341073728,
    "meanAbsoluteDeviationFrom50Mhz": 18.365833333333605
  },
  {
    "hour": 14,
    "validSamples": 3600,
    "averageHz": 50.00317861111111,
    "minimumHz": 49.967,
    "maximumHz": 50.049,
    "standardDeviationHz": 0.012965490017902547,
    "meanAbsoluteDeviationFrom50Mhz": 10.706944444444725
  },
  {
    "hour": 15,
    "validSamples": 3600,
    "averageHz": 50.00130222222222,
    "minimumHz": 49.947,
    "maximumHz": 50.062,
    "standardDeviationHz": 0.019459738937256634,
    "meanAbsoluteDeviationFrom50Mhz": 15.696111111111422
  },
  {
    "hour": 16,
    "validSamples": 3600,
    "averageHz": 50.007600277777776,
    "minimumHz": 49.935,
    "maximumHz": 50.106,
    "standardDeviationHz": 0.03855238067199479,
    "meanAbsoluteDeviationFrom50Mhz": 32.3380555555557
  },
  {
    "hour": 17,
    "validSamples": 3600,
    "averageHz": 50.01273361111111,
    "minimumHz": 49.941,
    "maximumHz": 50.137,
    "standardDeviationHz": 0.048182314450934724,
    "meanAbsoluteDeviationFrom50Mhz": 37.90416666666675
  },
  {
    "hour": 18,
    "validSamples": 3600,
    "averageHz": 50.00417777777778,
    "minimumHz": 49.949,
    "maximumHz": 50.076,
    "standardDeviationHz": 0.030087281468634486,
    "meanAbsoluteDeviationFrom50Mhz": 26.12000000000015
  },
  {
    "hour": 19,
    "validSamples": 3600,
    "averageHz": 49.99254055555556,
    "minimumHz": 49.937,
    "maximumHz": 50.086,
    "standardDeviationHz": 0.02940212614614093,
    "meanAbsoluteDeviationFrom50Mhz": 25.25944444444465
  },
  {
    "hour": 20,
    "validSamples": 3600,
    "averageHz": 49.99653333333333,
    "minimumHz": 49.919,
    "maximumHz": 50.046,
    "standardDeviationHz": 0.025905319059134593,
    "meanAbsoluteDeviationFrom50Mhz": 21.04888888888915
  },
  {
    "hour": 21,
    "validSamples": 3600,
    "averageHz": 50.009228888888885,
    "minimumHz": 49.91,
    "maximumHz": 50.065,
    "standardDeviationHz": 0.031016677393673475,
    "meanAbsoluteDeviationFrom50Mhz": 27.014444444444667
  },
  {
    "hour": 22,
    "validSamples": 3600,
    "averageHz": 49.99155944444445,
    "minimumHz": 49.908,
    "maximumHz": 50.033,
    "standardDeviationHz": 0.024420183358175748,
    "meanAbsoluteDeviationFrom50Mhz": 18.98611111111137
  },
  {
    "hour": 23,
    "validSamples": 3600,
    "averageHz": 50.004203333333336,
    "minimumHz": 49.914,
    "maximumHz": 50.058,
    "standardDeviationHz": 0.025576460314559353,
    "meanAbsoluteDeviationFrom50Mhz": 21.89000000000031
  }
]
